aiognmi/__init__.py
aiognmi/client.py
aiognmi/models.py
aiognmi/response.py
aiognmi/utils.py
aiognmi/proto/gnmi/gnmi_pb2.py
aiognmi/proto/gnmi/gnmi_pb2_grpc.py
aiognmi/proto/gnmi_ext/gnmi_ext_pb2.py
aiognmi/proto/gnmi_ext/gnmi_ext_pb2_grpc.py
tests/__init__.py
tests/test_utils.py
aiognmi-0.1.1.dist-info/LICENSE
aiognmi-0.1.1.dist-info/METADATA
aiognmi-0.1.1.dist-info/WHEEL
aiognmi-0.1.1.dist-info/top_level.txt
aiognmi-0.1.1.dist-info/RECORD
