Metadata-Version: 2.1
Name: aiognmi
Version: 0.1.1
Summary: Async, efficient and lightweight gNMI client written in Python.
Author: Artem Kotik
Author-email: miaow2@yandex.ru
License: MIT License
Project-URL: repository, https://github.com/miaow2/aiognmi/
Project-URL: homepage, https://github.com/miaow2/aiognmi/
Keywords: automation,network,network-automation,gnmi,gnmi-client,grpc,grpc-python,async,python
Classifier: Programming Language :: Python :: 3
Classifier: Programming Language :: Python :: 3 :: Only
Classifier: Programming Language :: Python :: 3.10
Classifier: Programming Language :: Python :: 3.11
Classifier: Programming Language :: Python :: 3.12
Classifier: Topic :: Software Development :: Libraries :: Python Modules
Classifier: Framework :: AsyncIO
Requires-Python: >=3.10
License-File: LICENSE
Requires-Dist: aiofile ==3.8.8
Requires-Dist: grpcio ==1.59.0
Requires-Dist: protobuf ==4.24.4
Provides-Extra: dev
Requires-Dist: ruff ==0.3.4 ; extra == 'dev'
Provides-Extra: publish
Requires-Dist: build ==1.2.1 ; extra == 'publish'
Requires-Dist: twine ==4.0.2 ; extra == 'publish'
Provides-Extra: test
Requires-Dist: pytest ==8.1.1 ; extra == 'test'
